odoo/addons/storage_image_product_brand/README.rst
odoo/addons/storage_image_product_brand/__init__.py
odoo/addons/storage_image_product_brand/__manifest__.py
odoo/addons/storage_image_product_brand/i18n/storage_image_product_brand.pot
odoo/addons/storage_image_product_brand/models/__init__.py
odoo/addons/storage_image_product_brand/models/image_tag.py
odoo/addons/storage_image_product_brand/models/product_brand.py
odoo/addons/storage_image_product_brand/models/product_brand_image_relation.py
odoo/addons/storage_image_product_brand/readme/CONTRIBUTORS.rst
odoo/addons/storage_image_product_brand/readme/DESCRIPTION.rst
odoo/addons/storage_image_product_brand/readme/USAGE.rst
odoo/addons/storage_image_product_brand/security/product_brand_image_relation.xml
odoo/addons/storage_image_product_brand/static/description/icon.png
odoo/addons/storage_image_product_brand/static/description/index.html
odoo/addons/storage_image_product_brand/views/product_brand.xml
odoo/addons/storage_image_product_brand/views/product_brand_image_relation.xml
odoo14_addon_storage_image_product_brand-14.0.2.0.0.dist-info/METADATA
odoo14_addon_storage_image_product_brand-14.0.2.0.0.dist-info/WHEEL
odoo14_addon_storage_image_product_brand-14.0.2.0.0.dist-info/top_level.txt
odoo14_addon_storage_image_product_brand-14.0.2.0.0.dist-info/RECORD
